django_compat_patcher/__init__.py
django_compat_patcher/config.py
django_compat_patcher/default_settings.py
django_compat_patcher/deprecation.py
django_compat_patcher/registry.py
django_compat_patcher/runner.py
django_compat_patcher/utilities.py
django_compat_patcher/django_legacy/__init__.py
django_compat_patcher/django_legacy/django1_10/__init__.py
django_compat_patcher/django_legacy/django1_10/template/__init__.py
django_compat_patcher/django_legacy/django1_10/template/defaulttags.py
django_compat_patcher/django_legacy/django1_10/templatetags/__init__.py
django_compat_patcher/django_legacy/django1_10/templatetags/future.py
django_compat_patcher/django_legacy/django1_9/__init__.py
django_compat_patcher/django_legacy/django1_9/datastructures.py
django_compat_patcher/django_legacy/django1_9/utils/__init__.py
django_compat_patcher/django_legacy/django1_9/utils/dictconfig.py
django_compat_patcher/django_legacy/django1_9/utils/functional.py
django_compat_patcher/django_legacy/django1_9/utils/importlib.py
django_compat_patcher/django_legacy/django1_9/utils/tzinfo.py
django_compat_patcher/django_legacy/django1_9/utils/unittest.py
django_compat_patcher/django_legacy/django2_0/__init__.py
django_compat_patcher/django_legacy/django2_0/utils/__init__.py
django_compat_patcher/django_legacy/django2_0/utils/deprecation.py
django_compat_patcher/django_legacy/django2_0/views/__init__.py
django_compat_patcher/django_legacy/django2_0/views/i18n.py
django_compat_patcher/django_legacy/django3_0/__init__.py
django_compat_patcher/django_legacy/django3_0/contrib__admin__templatetags__admin_static.py
django_compat_patcher/django_legacy/django3_0/lru_cache.py
django_compat_patcher/django_legacy/django3_0/contrib__staticfiles__templatetags__staticfiles/__init__.py
django_compat_patcher/django_legacy/django3_0/contrib__staticfiles__templatetags__staticfiles/staticfiles.py
django_compat_patcher/django_legacy/django4_0/__init__.py
django_compat_patcher-0.13.dist-info/licenses/AUTHORS
django_compat_patcher-0.13.dist-info/licenses/License.txt
django_compat_patcher-0.13.dist-info/METADATA
django_compat_patcher-0.13.dist-info/WHEEL
django_compat_patcher-0.13.dist-info/top_level.txt
django_compat_patcher-0.13.dist-info/RECORD
